multicopula/__init__.py
multicopula/multicopula.py
multicopula/tests/__init__.py
multicopula/utils/__init__.py
multicopula/utils/clustering_metrics.py
multicopula/utils/clustering_utils.py
multicopula/utils/copula_utils.py
multicopula/utils/time_series_utils.py
multicopula-0.0.2.dist-info/LICENSE
multicopula-0.0.2.dist-info/METADATA
multicopula-0.0.2.dist-info/WHEEL
multicopula-0.0.2.dist-info/top_level.txt
multicopula-0.0.2.dist-info/RECORD
