Metadata-Version: 2.1
Name: multicopula
Version: 0.0.2
Summary: Multivariate probability distributions using copula theory.
Author-email: e.m.salazar.duque@tue.nl
License: MIT
Project-URL: repository, https://github.com/MauricioSalazare/multi-copula
Keywords: uncertainty modelling,copula,multivariate probability,time series,load profiles,synthetic electrical loads
Classifier: Programming Language :: Python :: 3
Classifier: License :: OSI Approved :: MIT License
Classifier: Operating System :: OS Independent
Requires-Python: >=3.0
License-File: LICENSE
Requires-Dist: numpy
Requires-Dist: pandas
Requires-Dist: matplotlib
Requires-Dist: scipy
Requires-Dist: tqdm
Requires-Dist: scikit-learn
Requires-Dist: statsmodels
Requires-Dist: seaborn
Provides-Extra: dev
Requires-Dist: build ; extra == 'dev'
Requires-Dist: twine ; extra == 'dev'
Requires-Dist: jupyterlab ; extra == 'dev'
Provides-Extra: doc
Requires-Dist: sphinx ; extra == 'doc'
Provides-Extra: test
Requires-Dist: pytest ; extra == 'test'
